{"count": 20, "start": 0, "total": 79, "subjects": [{"rating": {"max": 10, "average": 0, "stars": "00", "min": 0}, "genres": ["\u5386\u53f2", "\u6218\u4e89"], "title": "\u5927\u4f1a\u5e08", "casts": [{"alt": "https:\/\/movie.douban.com\/celebrity\/1321811\/", "avatars": {"small": "https://img1.doubanio.com\/img\/celebrity\/small\/51437.jpg", "large": "https://img1.doubanio.com\/img\/celebrity\/large\/51437.jpg", "medium": "https://img1.doubanio.com\/img\/celebrity\/medium\/51437.jpg"}, "name": "\u738b\u6656", "id": "1321811"}, {"alt": "https:\/\/movie.douban.com\/celebrity\/1274228\/", "avatars": {"small": "https://img3.doubanio.com\/img\/celebrity\/small\/710.jpg", "large": "https://img3.doubanio.com\/img\/celebrity\/large\/710.jpg", "medium": "https://img3.doubanio.com\/img\/celebrity\/medium\/710.jpg"}, "name": "\u4faf\u52c7", "id": "1274228"}, {"alt": "https:\/\/movie.douban.com\/celebrity\/1318604\/", "avatars": {"small": "https://img3.doubanio.com\/img\/celebrity\/small\/1464835121.86.jpg", "large": "https://img3.doubanio.com\/img\/celebrity\/large\/1464835121.86.jpg", "medium": "https://img3.doubanio.com\/img\/celebrity\/medium\/1464835121.86.jpg"}, "name": "\u4faf\u7965\u73b2", "id": "1318604"}], "collect_count": 1, "original_title": "\u5927\u4f1a\u5e08", "subtype": "movie", "directors": [{"alt": "https:\/\/movie.douban.com\/celebrity\/1315152\/", "avatars": {"small": "https://img3.doubanio.com\/img\/celebrity\/small\/28955.jpg", "large": "https://img3.doubanio.com\/img\/celebrity\/large\/28955.jpg", "medium": "https://img3.doubanio.com\/img\/celebrity\/medium\/28955.jpg"}, "name": "\u5b89\u6f9c", "id": "1315152"}], "year": "2016", "images": {"small": "https://img3.doubanio.com\/view\/movie_poster_cover\/ipst\/public\/p2391136541.jpg", "large": "https://img3.doubanio.com\/view\/movie_poster_cover\/lpst\/public\/p2391136541.jpg", "medium": "https://img3.doubanio.com\/view\/movie_poster_cover\/spst\/public\/p2391136541.jpg"}, "alt": "https:\/\/movie.douban.com\/subject\/26897495\/", "id": "26897495"}, {"rating": {"max": 10, "average": 0, "stars": "00", "min": 0}, "genres": ["\u60ac\u7591", "\u60ca\u609a"], "title": "\u4f46\u4e01\u5bc6\u7801", "casts": [{"alt": "https:\/\/movie.douban.com\/celebrity\/1054450\/", "avatars": {"small": "https://img3.doubanio.com\/img\/celebrity\/small\/551.jpg", "large": "https://img3.doubanio.com\/img\/celebrity\/large\/551.jpg", "medium": "https://img3.doubanio.com\/img\/celebrity\/medium\/551.jpg"}, "name": "\u6c64\u59c6\u00b7\u6c49\u514b\u65af", "id": "1054450"}, {"alt": "https:\/\/movie.douban.com\/celebrity\/1013981\/", "avatars": {"small": "https://img3.doubanio.com\/img\/celebrity\/small\/42373.jpg", "large": "https://img3.doubanio.com\/img\/celebrity\/large\/42373.jpg", "medium": "https://img3.doubanio.com\/img\/celebrity\/medium\/42373.jpg"}, "name": "\u8d39\u8389\u897f\u8482\u00b7\u743c\u65af", "id": "1013981"}, {"alt": "https:\/\/movie.douban.com\/celebrity\/1040512\/", "avatars": {"small": "https://img3.doubanio.com\/img\/celebrity\/small\/2150.jpg", "large": "https://img3.doubanio.com\/img\/celebrity\/large\/2150.jpg", "medium": "https://img3.doubanio.com\/img\/celebrity\/medium\/2150.jpg"}, "name": "\u672c\u00b7\u798f\u65af\u7279", "id": "1040512"}], "collect_count": 464, "original_title": "Inferno", "subtype": "movie", "directors": [{"alt": "https:\/\/movie.douban.com\/celebrity\/1031844\/", "avatars": {"small": "https://img3.doubanio.com\/img\/celebrity\/small\/1366641135.85.jpg", "large": "https://img3.doubanio.com\/img\/celebrity\/large\/1366641135.85.jpg", "medium": "https://img3.doubanio.com\/img\/celebrity\/medium\/1366641135.85.jpg"}, "name": "\u6717\u00b7\u970d\u534e\u5fb7", "id": "1031844"}], "year": "2016", "images": {"small": "https://img3.doubanio.com\/view\/movie_poster_cover\/ipst\/public\/p2388072933.jpg", "large": "https://img3.doubanio.com\/view\/movie_poster_cover\/lpst\/public\/p2388072933.jpg", "medium": "https://img3.doubanio.com\/view\/movie_poster_cover\/spst\/public\/p2388072933.jpg"}, "alt": "https:\/\/movie.douban.com\/subject\/24860318\/", "id": "24860318"}, {"rating": {"max": 10, "average": 0, "stars": "00", "min": 0}, "genres": ["\u559c\u5267"], "title": "\u9a74\u5f97\u6c34", "casts": [{"alt": "https:\/\/movie.douban.com\/celebrity\/1362973\/", "avatars": {"small": "https://img1.doubanio.com\/img\/celebrity\/small\/1475988303.89.jpg", "large": "https://img1.doubanio.com\/img\/celebrity\/large\/1475988303.89.jpg", "medium": "https://img1.doubanio.com\/img\/celebrity\/medium\/1475988303.89.jpg"}, "name": "\u4efb\u7d20\u6c50", "id": "1362973"}, {"alt": "https:\/\/movie.douban.com\/celebrity\/1355797\/", "avatars": {"small": "https://img1.doubanio.com\/img\/celebrity\/small\/1458442004.38.jpg", "large": "https://img1.doubanio.com\/img\/celebrity\/large\/1458442004.38.jpg", "medium": "https://img1.doubanio.com\/img\/celebrity\/medium\/1458442004.38.jpg"}, "name": "\u5927\u529b", "id": "1355797"}, {"alt": "https:\/\/movie.douban.com\/celebrity\/1337891\/", "avatars": {"small": "https://img1.doubanio.com\/img\/celebrity\/small\/1392696207.67.jpg", "large": "https://img1.doubanio.com\/img\/celebrity\/large\/1392696207.67.jpg", "medium": "https://img1.doubanio.com\/img\/celebrity\/medium\/1392696207.67.jpg"}, "name": "\u5218\u5e05\u826f", "id": "1337891"}], "collect_count": 634, "original_title": "\u9a74\u5f97\u6c34", "subtype": "movie", "directors": [{"alt": "https:\/\/movie.douban.com\/celebrity\/1362256\/", "avatars": {"small": "https://img3.doubanio.com\/img\/celebrity\/small\/1475988453.85.jpg", "large": "https://img3.doubanio.com\/img\/celebrity\/large\/1475988453.85.jpg", "medium": "https://img3.doubanio.com\/img\/celebrity\/medium\/1475988453.85.jpg"}, "name": "\u5468\u7533", "id": "1362256"}, {"alt": "https:\/\/movie.douban.com\/celebrity\/1362257\/", "avatars": {"small": "https://img1.doubanio.com\/img\/celebrity\/small\/1475988524.57.jpg", "large": "https://img1.doubanio.com\/img\/celebrity\/large\/1475988524.57.jpg", "medium": "https://img1.doubanio.com\/img\/celebrity\/medium\/1475988524.57.jpg"}, "name": "\u5218\u9732", "id": "1362257"}], "year": "2016", "images": {"small": "https://img3.doubanio.com\/view\/movie_poster_cover\/ipst\/public\/p2387822905.jpg", "large": "https://img3.doubanio.com\/view\/movie_poster_cover\/lpst\/public\/p2387822905.jpg", "medium": "https://img3.doubanio.com\/view\/movie_poster_cover\/spst\/public\/p2387822905.jpg"}, "alt": "https:\/\/movie.douban.com\/subject\/25921812\/", "id": "25921812"}, {"rating": {"max": 10, "average": 0, "stars": "00", "min": 0}, "genres": ["\u52a8\u753b", "\u5947\u5e7b", "\u5192\u9669"], "title": "\u9b54\u53d1\u7cbe\u7075", "casts": [{"alt": "https:\/\/movie.douban.com\/celebrity\/1040987\/", "avatars": {"small": "https://img1.doubanio.com\/img\/celebrity\/small\/419.jpg", "large": "https://img1.doubanio.com\/img\/celebrity\/large\/419.jpg", "medium": "https://img1.doubanio.com\/img\/celebrity\/medium\/419.jpg"}, "name": "\u8d3e\u65af\u6c40\u00b7\u6c40\u5e03\u83b1\u514b", "id": "1040987"}, {"alt": "https:\/\/movie.douban.com\/celebrity\/1013789\/", "avatars": {"small": "https://img1.doubanio.com\/img\/celebrity\/small\/31847.jpg", "large": "https://img1.doubanio.com\/img\/celebrity\/large\/31847.jpg", "medium": "https://img1.doubanio.com\/img\/celebrity\/medium\/31847.jpg"}, "name": "\u5b89\u5a1c\u00b7\u80af\u5fb7\u91cc\u514b", "id": "1013789"}, {"alt": "https:\/\/movie.douban.com\/celebrity\/1017966\/", "avatars": {"small": "https://img3.doubanio.com\/img\/celebrity\/small\/1761.jpg", "large": "https://img3.doubanio.com\/img\/celebrity\/large\/1761.jpg", "medium": "https://img3.doubanio.com\/img\/celebrity\/medium\/1761.jpg"}, "name": "\u8a79\u59c6\u65af\u00b7\u67ef\u767b", "id": "1017966"}], "collect_count": 35, "original_title": "Trolls", "subtype": "movie", "directors": [{"alt": "https:\/\/movie.douban.com\/celebrity\/1292230\/", "avatars": {"small": "https://img1.doubanio.com\/f\/movie\/ca527386eb8c4e325611e22dfcb04cc116d6b423\/pics\/movie\/celebrity-default-small.png", "large": "https://img3.doubanio.com\/f\/movie\/63acc16ca6309ef191f0378faf793d1096a3e606\/pics\/movie\/celebrity-default-large.png", "medium": "https://img1.doubanio.com\/f\/movie\/8dd0c794499fe925ae2ae89ee30cd225750457b4\/pics\/movie\/celebrity-default-medium.png"}, "name": "\u8fc8\u514b\u00b7\u7c73\u6b47\u5c14", "id": "1292230"}, {"alt": null, "avatars": null, "name": "Walt Dohrn", "id": null}], "year": "2016", "images": {"small": "https://img3.doubanio.com\/view\/movie_poster_cover\/ipst\/public\/p2387527802.jpg", "large": "https://img3.doubanio.com\/view\/movie_poster_cover\/lpst\/public\/p2387527802.jpg", "medium": "https://img3.doubanio.com\/view\/movie_poster_cover\/spst\/public\/p2387527802.jpg"}, "alt": "https:\/\/movie.douban.com\/subject\/7065238\/", "id": "7065238"}, {"rating": {"max": 10, "average": 0, "stars": "00", "min": 0}, "genres": ["\u60ca\u609a", "\u6050\u6016"], "title": "\u6795\u8fb9\u6709\u5f20\u81382", "casts": [{"alt": "https:\/\/movie.douban.com\/celebrity\/1353049\/", "avatars": {"small": "https://img3.doubanio.com\/img\/celebrity\/small\/1448537867.92.jpg", "large": "https://img3.doubanio.com\/img\/celebrity\/large\/1448537867.92.jpg", "medium": "https://img3.doubanio.com\/img\/celebrity\/medium\/1448537867.92.jpg"}, "name": "\u8d75\u6167\u4ed9", "id": "1353049"}, {"alt": null, "avatars": null, "name": "\u7530\u5bb6\u5927", "id": null}, {"alt": null, "avatars": null, "name": "\u80e1\u777f", "id": null}], "collect_count": 33, "original_title": "\u6795\u8fb9\u6709\u5f20\u81382", "subtype": "movie", "directors": [{"alt": "https:\/\/movie.douban.com\/celebrity\/1323628\/", "avatars": {"small": "https://img3.doubanio.com\/img\/celebrity\/small\/1435833583.66.jpg", "large": "https://img3.doubanio.com\/img\/celebrity\/large\/1435833583.66.jpg", "medium": "https://img3.doubanio.com\/img\/celebrity\/medium\/1435833583.66.jpg"}, "name": "\u8d75\u5c0f\u6eaa", "id": "1323628"}], "year": "2016", "images": {"small": "https://img3.doubanio.com\/view\/movie_poster_cover\/ipst\/public\/p2384442426.jpg", "large": "https://img3.doubanio.com\/view\/movie_poster_cover\/lpst\/public\/p2384442426.jpg", "medium": "https://img3.doubanio.com\/view\/movie_poster_cover\/spst\/public\/p2384442426.jpg"}, "alt": "https:\/\/movie.douban.com\/subject\/26880771\/", "id": "26880771"}, {"rating": {"max": 10, "average": 0, "stars": "00", "min": 0}, "genres": ["\u60ca\u609a", "\u6050\u6016"], "title": "\u80b2\u5a74\u5ba4", "casts": [{"alt": "https:\/\/movie.douban.com\/celebrity\/1316703\/", "avatars": {"small": "https://img1.doubanio.com\/img\/celebrity\/small\/1421138015.79.jpg", "large": "https://img1.doubanio.com\/img\/celebrity\/large\/1421138015.79.jpg", "medium": "https://img1.doubanio.com\/img\/celebrity\/medium\/1421138015.79.jpg"}, "name": "\u90b1\u654f\u654f", "id": "1316703"}, {"alt": "https:\/\/movie.douban.com\/celebrity\/1318883\/", "avatars": {"small": "https://img3.doubanio.com\/img\/celebrity\/small\/1469384955.41.jpg", "large": "https://img3.doubanio.com\/img\/celebrity\/large\/1469384955.41.jpg", "medium": "https://img3.doubanio.com\/img\/celebrity\/medium\/1469384955.41.jpg"}, "name": "\u6731\u4e00\u9f99", "id": "1318883"}, {"alt": "https:\/\/movie.douban.com\/celebrity\/1315812\/", "avatars": {"small": "https://img3.doubanio.com\/img\/celebrity\/small\/39261.jpg", "large": "https://img3.doubanio.com\/img\/celebrity\/large\/39261.jpg", "medium": "https://img3.doubanio.com\/img\/celebrity\/medium\/39261.jpg"}, "name": "\u5f90\u6d01\u513f", "id": "1315812"}], "collect_count": 53, "original_title": "\u80b2\u5a74\u5ba4", "subtype": "movie", "directors": [{"alt": "https:\/\/movie.douban.com\/celebrity\/1327529\/", "avatars": {"small": "https://img1.doubanio.com\/f\/movie\/ca527386eb8c4e325611e22dfcb04cc116d6b423\/pics\/movie\/celebrity-default-small.png", "large": "https://img3.doubanio.com\/f\/movie\/63acc16ca6309ef191f0378faf793d1096a3e606\/pics\/movie\/celebrity-default-large.png", "medium": "https://img1.doubanio.com\/f\/movie\/8dd0c794499fe925ae2ae89ee30cd225750457b4\/pics\/movie\/celebrity-default-medium.png"}, "name": "\u76ae\u67e5\u519c\u00b7\u5854\u739b\u6770\u62c9", "id": "1327529"}], "year": "2016", "images": {"small": "https://img3.doubanio.com\/view\/movie_poster_cover\/ipst\/public\/p2372301645.jpg", "large": "https://img3.doubanio.com\/view\/movie_poster_cover\/lpst\/public\/p2372301645.jpg", "medium": "https://img3.doubanio.com\/view\/movie_poster_cover\/spst\/public\/p2372301645.jpg"}, "alt": "https:\/\/movie.douban.com\/subject\/26318896\/", "id": "26318896"}, {"rating": {"max": 10, "average": 7.2, "stars": "35", "min": 0}, "genres": ["\u5267\u60c5"], "title": "\u5bfc\u706b\u65b0\u95fb\u7ebf", "casts": [{"alt": "https:\/\/movie.douban.com\/celebrity\/1016771\/", "avatars": {"small": "https://img3.doubanio.com\/img\/celebrity\/small\/45481.jpg", "large": "https://img3.doubanio.com\/img\/celebrity\/large\/45481.jpg", "medium": "https://img3.doubanio.com\/img\/celebrity\/medium\/45481.jpg"}, "name": "\u5434\u5b5f\u8fbe", "id": "1016771"}, {"alt": "https:\/\/movie.douban.com\/celebrity\/1321491\/", "avatars": {"small": "https://img1.doubanio.com\/img\/celebrity\/small\/1430325832.7.jpg", "large": "https://img1.doubanio.com\/img\/celebrity\/large\/1430325832.7.jpg", "medium": "https://img1.doubanio.com\/img\/celebrity\/medium\/1430325832.7.jpg"}, "name": "\u5468\u5bb6\u6021", "id": "1321491"}, {"alt": "https:\/\/movie.douban.com\/celebrity\/1305834\/", "avatars": {"small": "https://img3.doubanio.com\/img\/celebrity\/small\/1355903796.03.jpg", "large": "https://img3.doubanio.com\/img\/celebrity\/large\/1355903796.03.jpg", "medium": "https://img3.doubanio.com\/img\/celebrity\/medium\/1355903796.03.jpg"}, "name": "\u6768\u6dc7", "id": "1305834"}], "collect_count": 96, "original_title": "\u5c0e\u706b\u65b0\u805e\u7dda", "subtype": "movie", "directors": [{"alt": null, "avatars": null, "name": "\u65b9\u4fca\u534e", "id": null}], "year": "2016", "images": {"small": "https://img3.doubanio.com\/view\/movie_poster_cover\/ipst\/public\/p2386843341.jpg", "large": "https://img3.doubanio.com\/view\/movie_poster_cover\/lpst\/public\/p2386843341.jpg", "medium": "https://img3.doubanio.com\/view\/movie_poster_cover\/spst\/public\/p2386843341.jpg"}, "alt": "https:\/\/movie.douban.com\/subject\/26717012\/", "id": "26717012"}, {"rating": {"max": 10, "average": 0, "stars": "00", "min": 0}, "genres": ["\u559c\u5267"], "title": "\u5c0f\u660e\u548c\u4ed6\u7684\u5c0f\u4f19\u4f34\u4eec", "casts": [{"alt": "https:\/\/movie.douban.com\/celebrity\/1316368\/", "avatars": {"small": "https://img3.doubanio.com\/img\/celebrity\/small\/1473410979.5.jpg", "large": "https://img3.doubanio.com\/img\/celebrity\/large\/1473410979.5.jpg", "medium": "https://img3.doubanio.com\/img\/celebrity\/medium\/1473410979.5.jpg"}, "name": "\u4e54\u6749", "id": "1316368"}, {"alt": "https:\/\/movie.douban.com\/celebrity\/1362516\/", "avatars": {"small": "https://img3.doubanio.com\/img\/celebrity\/small\/1474529068.86.jpg", "large": "https://img3.doubanio.com\/img\/celebrity\/large\/1474529068.86.jpg", "medium": "https://img3.doubanio.com\/img\/celebrity\/medium\/1474529068.86.jpg"}, "name": "\u8bb8\u541b\u806a", "id": "1362516"}, {"alt": "https:\/\/movie.douban.com\/celebrity\/1362518\/", "avatars": {"small": "https://img3.doubanio.com\/img\/celebrity\/small\/1474529389.5.jpg", "large": "https://img3.doubanio.com\/img\/celebrity\/large\/1474529389.5.jpg", "medium": "https://img3.doubanio.com\/img\/celebrity\/medium\/1474529389.5.jpg"}, "name": "\u8d39\u4f1f\u59ae", "id": "1362518"}], "collect_count": 31, "original_title": "\u5c0f\u660e\u548c\u4ed6\u7684\u5c0f\u4f19\u4f34\u4eec", "subtype": "movie", "directors": [{"alt": null, "avatars": null, "name": "\u738b\u946b", "id": null}], "year": "2016", "images": {"small": "https://img3.doubanio.com\/view\/movie_poster_cover\/ipst\/public\/p2382206861.jpg", "large": "https://img3.doubanio.com\/view\/movie_poster_cover\/lpst\/public\/p2382206861.jpg", "medium": "https://img3.doubanio.com\/view\/movie_poster_cover\/spst\/public\/p2382206861.jpg"}, "alt": "https:\/\/movie.douban.com\/subject\/26869052\/", "id": "26869052"}, {"rating": {"max": 10, "average": 0, "stars": "00", "min": 0}, "genres": ["\u5267\u60c5", "\u6218\u4e89"], "title": "\u4f55\u53bb\u4f55\u4ece", "casts": [{"alt": "https:\/\/movie.douban.com\/celebrity\/1313655\/", "avatars": {"small": "https://img1.doubanio.com\/img\/celebrity\/small\/42407.jpg", "large": "https://img1.doubanio.com\/img\/celebrity\/large\/42407.jpg", "medium": "https://img1.doubanio.com\/img\/celebrity\/medium\/42407.jpg"}, "name": "\u4e2d\u6cc9\u82f1\u96c4", "id": "1313655"}, {"alt": null, "avatars": null, "name": "\u6f06\u5b50\u7f8e", "id": null}, {"alt": "https:\/\/movie.douban.com\/celebrity\/1336630\/", "avatars": {"small": "https://img1.doubanio.com\/img\/celebrity\/small\/1442643624.48.jpg", "large": "https://img1.doubanio.com\/img\/celebrity\/large\/1442643624.48.jpg", "medium": "https://img1.doubanio.com\/img\/celebrity\/medium\/1442643624.48.jpg"}, "name": "\u674e\u5a73", "id": "1336630"}], "collect_count": 15, "original_title": "\u4f55\u53bb\u4f55\u4ece", "subtype": "movie", "directors": [{"alt": null, "avatars": null, "name": "\u5173\u6676", "id": null}], "year": "2016", "images": {"small": "https://img3.doubanio.com\/view\/movie_poster_cover\/ipst\/public\/p2390248405.jpg", "large": "https://img3.doubanio.com\/view\/movie_poster_cover\/lpst\/public\/p2390248405.jpg", "medium": "https://img3.doubanio.com\/view\/movie_poster_cover\/spst\/public\/p2390248405.jpg"}, "alt": "https:\/\/movie.douban.com\/subject\/26581128\/", "id": "26581128"}, {"rating": {"max": 10, "average": 0, "stars": "00", "min": 0}, "genres": ["\u60ca\u609a", "\u6050\u6016"], "title": "\u6050\u6016\u7b14\u8bb0", "casts": [{"alt": "https:\/\/movie.douban.com\/celebrity\/1324188\/", "avatars": {"small": "https://img3.doubanio.com\/img\/celebrity\/small\/1396248458.84.jpg", "large": "https://img3.doubanio.com\/img\/celebrity\/large\/1396248458.84.jpg", "medium": "https://img3.doubanio.com\/img\/celebrity\/medium\/1396248458.84.jpg"}, "name": "\u8d75\u6cf3\u946b", "id": "1324188"}, {"alt": "https:\/\/movie.douban.com\/celebrity\/1321055\/", "avatars": {"small": "https://img1.doubanio.com\/img\/celebrity\/small\/50068.jpg", "large": "https://img1.doubanio.com\/img\/celebrity\/large\/50068.jpg", "medium": "https://img1.doubanio.com\/img\/celebrity\/medium\/50068.jpg"}, "name": "\u6a80\u5065\u6b21", "id": "1321055"}, {"alt": "https:\/\/movie.douban.com\/celebrity\/1337324\/", "avatars": {"small": "https://img3.doubanio.com\/img\/celebrity\/small\/1390480054.14.jpg", "large": "https://img3.doubanio.com\/img\/celebrity\/large\/1390480054.14.jpg", "medium": "https://img3.doubanio.com\/img\/celebrity\/medium\/1390480054.14.jpg"}, "name": "\u51af\u5bb6\u59b9", "id": "1337324"}], "collect_count": 45, "original_title": "\u6050\u6016\u7b14\u8bb0", "subtype": "movie", "directors": [{"alt": "https:\/\/movie.douban.com\/celebrity\/1359365\/", "avatars": {"small": "https://img1.doubanio.com\/f\/movie\/ca527386eb8c4e325611e22dfcb04cc116d6b423\/pics\/movie\/celebrity-default-small.png", "large": "https://img3.doubanio.com\/f\/movie\/63acc16ca6309ef191f0378faf793d1096a3e606\/pics\/movie\/celebrity-default-large.png", "medium": "https://img1.doubanio.com\/f\/movie\/8dd0c794499fe925ae2ae89ee30cd225750457b4\/pics\/movie\/celebrity-default-medium.png"}, "name": "\u95f5\u664b\u6d9b", "id": "1359365"}], "year": "2016", "images": {"small": "https://img3.doubanio.com\/view\/movie_poster_cover\/ipst\/public\/p2389179356.jpg", "large": "https://img3.doubanio.com\/view\/movie_poster_cover\/lpst\/public\/p2389179356.jpg", "medium": "https://img3.doubanio.com\/view\/movie_poster_cover\/spst\/public\/p2389179356.jpg"}, "alt": "https:\/\/movie.douban.com\/subject\/25953613\/", "id": "25953613"}, {"rating": {"max": 10, "average": 0, "stars": "00", "min": 0}, "genres": ["\u513f\u7ae5", "\u559c\u5267", "\u52a8\u753b"], "title": "\u529f\u592b\u56db\u4fa0", "casts": [{"alt": "https:\/\/movie.douban.com\/celebrity\/1359920\/", "avatars": {"small": "https://img3.doubanio.com\/img\/celebrity\/small\/1468223589.2.jpg", "large": "https://img3.doubanio.com\/img\/celebrity\/large\/1468223589.2.jpg", "medium": "https://img3.doubanio.com\/img\/celebrity\/medium\/1468223589.2.jpg"}, "name": "\u5f90\u5eb7", "id": "1359920"}, {"alt": "https:\/\/movie.douban.com\/celebrity\/1345272\/", "avatars": {"small": "https://img3.doubanio.com\/img\/celebrity\/small\/1468222995.05.jpg", "large": "https://img3.doubanio.com\/img\/celebrity\/large\/1468222995.05.jpg", "medium": "https://img3.doubanio.com\/img\/celebrity\/medium\/1468222995.05.jpg"}, "name": "\u6731\u84c9\u84c9", "id": "1345272"}], "collect_count": 48, "original_title": "\u529f\u592b\u56db\u4fa0", "subtype": "movie", "directors": [{"alt": "https:\/\/movie.douban.com\/celebrity\/1359893\/", "avatars": {"small": "https://img1.doubanio.com\/img\/celebrity\/small\/1468218084.77.jpg", "large": "https://img1.doubanio.com\/img\/celebrity\/large\/1468218084.77.jpg", "medium": "https://img1.doubanio.com\/img\/celebrity\/medium\/1468218084.77.jpg"}, "name": "\u5218\u90a6\u90a6", "id": "1359893"}, {"alt": "https:\/\/movie.douban.com\/celebrity\/1359894\/", "avatars": {"small": "https://img1.doubanio.com\/img\/celebrity\/small\/1468218137.08.jpg", "large": "https://img1.doubanio.com\/img\/celebrity\/large\/1468218137.08.jpg", "medium": "https://img1.doubanio.com\/img\/celebrity\/medium\/1468218137.08.jpg"}, "name": "\u5b59\u53cb\u6811", "id": "1359894"}], "year": "2016", "images": {"small": "https://img3.doubanio.com\/view\/movie_poster_cover\/ipst\/public\/p2367924473.jpg", "large": "https://img3.doubanio.com\/view\/movie_poster_cover\/lpst\/public\/p2367924473.jpg", "medium": "https://img3.doubanio.com\/view\/movie_poster_cover\/spst\/public\/p2367924473.jpg"}, "alt": "https:\/\/movie.douban.com\/subject\/26831514\/", "id": "26831514"}, {"rating": {"max": 10, "average": 6.8, "stars": "35", "min": 0}, "genres": ["\u5267\u60c5", "\u52a8\u4f5c", "\u60ac\u7591"], "title": "\u8111\u6b8b\u7c89", "casts": [{"alt": "https:\/\/movie.douban.com\/celebrity\/1041117\/", "avatars": {"small": "https://img1.doubanio.com\/img\/celebrity\/small\/1479.jpg", "large": "https://img1.doubanio.com\/img\/celebrity\/large\/1479.jpg", "medium": "https://img1.doubanio.com\/img\/celebrity\/medium\/1479.jpg"}, "name": "\u6c99\u9c81\u514b\u00b7\u6c57", "id": "1041117"}, {"alt": "https:\/\/movie.douban.com\/celebrity\/1325052\/", "avatars": {"small": "https://img3.doubanio.com\/img\/celebrity\/small\/1353463815.65.jpg", "large": "https://img3.doubanio.com\/img\/celebrity\/large\/1353463815.65.jpg", "medium": "https://img3.doubanio.com\/img\/celebrity\/medium\/1353463815.65.jpg"}, "name": "\u4f0a\u5229\u4e9a\u5a1c\u00b7\u72c4\u514b\u9c81\u5179", "id": "1325052"}, {"alt": "https:\/\/movie.douban.com\/celebrity\/1338020\/", "avatars": {"small": "https://img1.doubanio.com\/img\/celebrity\/small\/214kd2VnJocel_avatar_uploaded1392369876.19.jpg", "large": "https://img1.doubanio.com\/img\/celebrity\/large\/214kd2VnJocel_avatar_uploaded1392369876.19.jpg", "medium": "https://img1.doubanio.com\/img\/celebrity\/medium\/214kd2VnJocel_avatar_uploaded1392369876.19.jpg"}, "name": "\u74e6\u59ae\u00b7\u5361\u666e\u5c14", "id": "1338020"}], "collect_count": 460, "original_title": "Fan", "subtype": "movie", "directors": [{"alt": "https:\/\/movie.douban.com\/celebrity\/1334355\/", "avatars": {"small": "https://img1.doubanio.com\/f\/movie\/ca527386eb8c4e325611e22dfcb04cc116d6b423\/pics\/movie\/celebrity-default-small.png", "large": "https://img3.doubanio.com\/f\/movie\/63acc16ca6309ef191f0378faf793d1096a3e606\/pics\/movie\/celebrity-default-large.png", "medium": "https://img1.doubanio.com\/f\/movie\/8dd0c794499fe925ae2ae89ee30cd225750457b4\/pics\/movie\/celebrity-default-medium.png"}, "name": "\u739b\u5c3c\u4ec0\u00b7\u838e\u739b", "id": "1334355"}], "year": "2016", "images": {"small": "https://img3.doubanio.com\/view\/movie_poster_cover\/ipst\/public\/p2358671873.jpg", "large": "https://img3.doubanio.com\/view\/movie_poster_cover\/lpst\/public\/p2358671873.jpg", "medium": "https://img3.doubanio.com\/view\/movie_poster_cover\/spst\/public\/p2358671873.jpg"}, "alt": "https:\/\/movie.douban.com\/subject\/25824009\/", "id": "25824009"}, {"rating": {"max": 10, "average": 8.5, "stars": "45", "min": 0}, "genres": ["\u52a8\u4f5c", "\u79d1\u5e7b"], "title": "\u7ec8\u7ed3\u80052\uff1a\u5ba1\u5224\u65e5", "casts": [{"alt": "https:\/\/movie.douban.com\/celebrity\/1035643\/", "avatars": {"small": "https://img1.doubanio.com\/img\/celebrity\/small\/989.jpg", "large": "https://img1.doubanio.com\/img\/celebrity\/large\/989.jpg", "medium": "https://img1.doubanio.com\/img\/celebrity\/medium\/989.jpg"}, "name": "\u963f\u8bfa\u00b7\u65bd\u74e6\u8f9b\u683c", "id": "1035643"}, {"alt": "https:\/\/movie.douban.com\/celebrity\/1027821\/", "avatars": {"small": "https://img1.doubanio.com\/img\/celebrity\/small\/45249.jpg", "large": "https://img1.doubanio.com\/img\/celebrity\/large\/45249.jpg", "medium": "https://img1.doubanio.com\/img\/celebrity\/medium\/45249.jpg"}, "name": "\u7433\u8fbe\u00b7\u6c49\u5bc6\u5c14\u987f", "id": "1027821"}, {"alt": "https:\/\/movie.douban.com\/celebrity\/1022600\/", "avatars": {"small": "https://img3.doubanio.com\/img\/celebrity\/small\/20874.jpg", "large": "https://img3.doubanio.com\/img\/celebrity\/large\/20874.jpg", "medium": "https://img3.doubanio.com\/img\/celebrity\/medium\/20874.jpg"}, "name": "\u7231\u5fb7\u534e\u00b7\u798f\u9686", "id": "1022600"}], "collect_count": 168184, "original_title": "Terminator 2: Judgment Day", "subtype": "movie", "directors": [{"alt": "https:\/\/movie.douban.com\/celebrity\/1022571\/", "avatars": {"small": "https://img3.doubanio.com\/img\/celebrity\/small\/33715.jpg", "large": "https://img3.doubanio.com\/img\/celebrity\/large\/33715.jpg", "medium": "https://img3.doubanio.com\/img\/celebrity\/medium\/33715.jpg"}, "name": "\u8a79\u59c6\u65af\u00b7\u5361\u6885\u9686", "id": "1022571"}], "year": "1991", "images": {"small": "https://img3.doubanio.com\/view\/movie_poster_cover\/ipst\/public\/p1910909085.jpg", "large": "https://img3.doubanio.com\/view\/movie_poster_cover\/lpst\/public\/p1910909085.jpg", "medium": "https://img3.doubanio.com\/view\/movie_poster_cover\/spst\/public\/p1910909085.jpg"}, "alt": "https:\/\/movie.douban.com\/subject\/1291844\/", "id": "1291844"}, {"rating": {"max": 10, "average": 0, "stars": "00", "min": 0}, "genres": ["\u5192\u9669", "\u5947\u5e7b"], "title": "\u5947\u5f02\u535a\u58eb", "casts": [{"alt": "https:\/\/movie.douban.com\/celebrity\/1009405\/", "avatars": {"small": "https://img3.doubanio.com\/img\/celebrity\/small\/41072.jpg", "large": "https://img3.doubanio.com\/img\/celebrity\/large\/41072.jpg", "medium": "https://img3.doubanio.com\/img\/celebrity\/medium\/41072.jpg"}, "name": "\u672c\u5c3c\u8fea\u514b\u7279\u00b7\u5eb7\u4f2f\u5df4\u5947", "id": "1009405"}, {"alt": "https:\/\/movie.douban.com\/celebrity\/1025152\/", "avatars": {"small": "https://img3.doubanio.com\/img\/celebrity\/small\/3546.jpg", "large": "https://img3.doubanio.com\/img\/celebrity\/large\/3546.jpg", "medium": "https://img3.doubanio.com\/img\/celebrity\/medium\/3546.jpg"}, "name": "\u8482\u5c14\u8fbe\u00b7\u65af\u6587\u987f", "id": "1025152"}, {"alt": "https:\/\/movie.douban.com\/celebrity\/1040529\/", "avatars": {"small": "https://img3.doubanio.com\/img\/celebrity\/small\/57893.jpg", "large": "https://img3.doubanio.com\/img\/celebrity\/large\/57893.jpg", "medium": "https://img3.doubanio.com\/img\/celebrity\/medium\/57893.jpg"}, "name": "\u9ea6\u65af\u00b7\u7c73\u79d1\u5c14\u68ee", "id": "1040529"}], "collect_count": 221, "original_title": "Doctor Strange", "subtype": "movie", "directors": [{"alt": "https:\/\/movie.douban.com\/celebrity\/1320372\/", "avatars": {"small": "https://img1.doubanio.com\/img\/celebrity\/small\/49077.jpg", "large": "https://img1.doubanio.com\/img\/celebrity\/large\/49077.jpg", "medium": "https://img1.doubanio.com\/img\/celebrity\/medium\/49077.jpg"}, "name": "\u65af\u79d1\u7279\u00b7\u5fb7\u745e\u514b\u68ee", "id": "1320372"}], "year": "2016", "images": {"small": "https://img1.doubanio.com\/view\/movie_poster_cover\/ipst\/public\/p2388132117.jpg", "large": "https://img1.doubanio.com\/view\/movie_poster_cover\/lpst\/public\/p2388132117.jpg", "medium": "https://img1.doubanio.com\/view\/movie_poster_cover\/spst\/public\/p2388132117.jpg"}, "alt": "https:\/\/movie.douban.com\/subject\/3025375\/", "id": "3025375"}, {"rating": {"max": 10, "average": 0, "stars": "00", "min": 0}, "genres": ["\u5267\u60c5", "\u60ac\u7591", "\u60ca\u609a"], "title": "\u6349\u8ff7\u85cf", "casts": [{"alt": "https:\/\/movie.douban.com\/celebrity\/1015713\/", "avatars": {"small": "https://img3.doubanio.com\/img\/celebrity\/small\/1414655610.66.jpg", "large": "https://img3.doubanio.com\/img\/celebrity\/large\/1414655610.66.jpg", "medium": "https://img3.doubanio.com\/img\/celebrity\/medium\/1414655610.66.jpg"}, "name": "\u970d\u5efa\u534e", "id": "1015713"}, {"alt": "https:\/\/movie.douban.com\/celebrity\/1274437\/", "avatars": {"small": "https://img3.doubanio.com\/img\/celebrity\/small\/48635.jpg", "large": "https://img3.doubanio.com\/img\/celebrity\/large\/48635.jpg", "medium": "https://img3.doubanio.com\/img\/celebrity\/medium\/48635.jpg"}, "name": "\u79e6\u6d77\u7490", "id": "1274437"}, {"alt": "https:\/\/movie.douban.com\/celebrity\/1315477\/", "avatars": {"small": "https://img3.doubanio.com\/img\/celebrity\/small\/1409894362.63.jpg", "large": "https://img3.doubanio.com\/img\/celebrity\/large\/1409894362.63.jpg", "medium": "https://img3.doubanio.com\/img\/celebrity\/medium\/1409894362.63.jpg"}, "name": "\u4e07\u831c", "id": "1315477"}], "collect_count": 106, "original_title": "\u6349\u8ff7\u85cf", "subtype": "movie", "directors": [{"alt": "https:\/\/movie.douban.com\/celebrity\/1274348\/", "avatars": {"small": "https://img1.doubanio.com\/img\/celebrity\/small\/1372060655.97.jpg", "large": "https://img1.doubanio.com\/img\/celebrity\/large\/1372060655.97.jpg", "medium": "https://img1.doubanio.com\/img\/celebrity\/medium\/1372060655.97.jpg"}, "name": "\u5218\u6770", "id": "1274348"}], "year": "2016", "images": {"small": "https://img3.doubanio.com\/view\/movie_poster_cover\/ipst\/public\/p2388060654.jpg", "large": "https://img3.doubanio.com\/view\/movie_poster_cover\/lpst\/public\/p2388060654.jpg", "medium": "https://img3.doubanio.com\/view\/movie_poster_cover\/spst\/public\/p2388060654.jpg"}, "alt": "https:\/\/movie.douban.com\/subject\/26757373\/", "id": "26757373"}, {"rating": {"max": 10, "average": 0, "stars": "00", "min": 0}, "genres": ["\u5267\u60c5", "\u7231\u60c5", "\u5bb6\u5ead"], "title": "\u4e00\u53e5\u9876\u4e00\u4e07\u53e5", "casts": [{"alt": "https:\/\/movie.douban.com\/celebrity\/1315488\/", "avatars": {"small": "https://img1.doubanio.com\/img\/celebrity\/small\/1458782554.68.jpg", "large": "https://img1.doubanio.com\/img\/celebrity\/large\/1458782554.68.jpg", "medium": "https://img1.doubanio.com\/img\/celebrity\/medium\/1458782554.68.jpg"}, "name": "\u6bdb\u5b69", "id": "1315488"}, {"alt": "https:\/\/movie.douban.com\/celebrity\/1313760\/", "avatars": {"small": "https://img1.doubanio.com\/img\/celebrity\/small\/1411387657.99.jpg", "large": "https://img1.doubanio.com\/img\/celebrity\/large\/1411387657.99.jpg", "medium": "https://img1.doubanio.com\/img\/celebrity\/medium\/1411387657.99.jpg"}, "name": "\u674e\u5029", "id": "1313760"}, {"alt": "https:\/\/movie.douban.com\/celebrity\/1304661\/", "avatars": {"small": "https://img3.doubanio.com\/img\/celebrity\/small\/27755.jpg", "large": "https://img3.doubanio.com\/img\/celebrity\/large\/27755.jpg", "medium": "https://img3.doubanio.com\/img\/celebrity\/medium\/27755.jpg"}, "name": "\u5218\u84d3", "id": "1304661"}], "collect_count": 103, "original_title": "\u4e00\u53e5\u9876\u4e00\u4e07\u53e5", "subtype": "movie", "directors": [{"alt": "https:\/\/movie.douban.com\/celebrity\/1361863\/", "avatars": {"small": "https://img3.doubanio.com\/img\/celebrity\/small\/6hKOEUaShmkcel_avatar_uploaded1472732748.85.jpg", "large": "https://img3.doubanio.com\/img\/celebrity\/large\/6hKOEUaShmkcel_avatar_uploaded1472732748.85.jpg", "medium": "https://img3.doubanio.com\/img\/celebrity\/medium\/6hKOEUaShmkcel_avatar_uploaded1472732748.85.jpg"}, "name": "\u5218\u96e8\u9716", "id": "1361863"}], "year": "2016", "images": {"small": "https://img3.doubanio.com\/view\/movie_poster_cover\/ipst\/public\/p2389970856.jpg", "large": "https://img3.doubanio.com\/view\/movie_poster_cover\/lpst\/public\/p2389970856.jpg", "medium": "https://img3.doubanio.com\/view\/movie_poster_cover\/spst\/public\/p2389970856.jpg"}, "alt": "https:\/\/movie.douban.com\/subject\/26389466\/", "id": "26389466"}, {"rating": {"max": 10, "average": 0, "stars": "00", "min": 0}, "genres": ["\u5267\u60c5", "\u559c\u5267", "\u7231\u60c5"], "title": "\u4e0d\u79bb\u4e0d\u5f03", "casts": [{"alt": "https:\/\/movie.douban.com\/celebrity\/1315027\/", "avatars": {"small": "https://img1.doubanio.com\/img\/celebrity\/small\/27989.jpg", "large": "https://img1.doubanio.com\/img\/celebrity\/large\/27989.jpg", "medium": "https://img1.doubanio.com\/img\/celebrity\/medium\/27989.jpg"}, "name": "\u8881\u6210\u6770", "id": "1315027"}, {"alt": "https:\/\/movie.douban.com\/celebrity\/1318973\/", "avatars": {"small": "https://img3.doubanio.com\/img\/celebrity\/small\/45144.jpg", "large": "https://img3.doubanio.com\/img\/celebrity\/large\/45144.jpg", "medium": "https://img3.doubanio.com\/img\/celebrity\/medium\/45144.jpg"}, "name": "\u66f9\u4e91\u91d1", "id": "1318973"}, {"alt": "https:\/\/movie.douban.com\/celebrity\/1275719\/", "avatars": {"small": "https://img3.doubanio.com\/img\/celebrity\/small\/33404.jpg", "large": "https://img3.doubanio.com\/img\/celebrity\/large\/33404.jpg", "medium": "https://img3.doubanio.com\/img\/celebrity\/medium\/33404.jpg"}, "name": "\u6c5f\u82e5\u7433", "id": "1275719"}], "collect_count": 11, "original_title": "\u4e0d\u79bb\u4e0d\u5f03", "subtype": "movie", "directors": [{"alt": "https:\/\/movie.douban.com\/celebrity\/1317479\/", "avatars": {"small": "https://img3.doubanio.com\/img\/celebrity\/small\/40005.jpg", "large": "https://img3.doubanio.com\/img\/celebrity\/large\/40005.jpg", "medium": "https://img3.doubanio.com\/img\/celebrity\/medium\/40005.jpg"}, "name": "\u848b\u94a6\u6c11", "id": "1317479"}], "year": "2016", "images": {"small": "https://img3.doubanio.com\/view\/movie_poster_cover\/ipst\/public\/p2390063620.jpg", "large": "https://img3.doubanio.com\/view\/movie_poster_cover\/lpst\/public\/p2390063620.jpg", "medium": "https://img3.doubanio.com\/view\/movie_poster_cover\/spst\/public\/p2390063620.jpg"}, "alt": "https:\/\/movie.douban.com\/subject\/26828548\/", "id": "26828548"}, {"rating": {"max": 10, "average": 0, "stars": "00", "min": 0}, "genres": ["\u5267\u60c5", "\u559c\u5267", "\u7231\u60c5"], "title": "\u975e\u5e38\u7236\u5b50\u6863", "casts": [{"alt": "https:\/\/movie.douban.com\/celebrity\/1274292\/", "avatars": {"small": "https://img3.doubanio.com\/img\/celebrity\/small\/10300.jpg", "large": "https://img3.doubanio.com\/img\/celebrity\/large\/10300.jpg", "medium": "https://img3.doubanio.com\/img\/celebrity\/medium\/10300.jpg"}, "name": "\u674e\u6cbb\u5ef7", "id": "1274292"}, {"alt": "https:\/\/movie.douban.com\/celebrity\/1107868\/", "avatars": {"small": "https://img1.doubanio.com\/img\/celebrity\/small\/40858.jpg", "large": "https://img1.doubanio.com\/img\/celebrity\/large\/40858.jpg", "medium": "https://img1.doubanio.com\/img\/celebrity\/medium\/40858.jpg"}, "name": "\u91d1\u8377\u5a1c", "id": "1107868"}, {"alt": "https:\/\/movie.douban.com\/celebrity\/1313976\/", "avatars": {"small": "https://img3.doubanio.com\/img\/celebrity\/small\/26441.jpg", "large": "https://img3.doubanio.com\/img\/celebrity\/large\/26441.jpg", "medium": "https://img3.doubanio.com\/img\/celebrity\/medium\/26441.jpg"}, "name": "\u6587\u6885\u68ee", "id": "1313976"}], "collect_count": 20, "original_title": "\u975e\u5e38\u7236\u5b50\u6863", "subtype": "movie", "directors": [{"alt": "https:\/\/movie.douban.com\/celebrity\/1345724\/", "avatars": {"small": "https://img1.doubanio.com\/f\/movie\/ca527386eb8c4e325611e22dfcb04cc116d6b423\/pics\/movie\/celebrity-default-small.png", "large": "https://img3.doubanio.com\/f\/movie\/63acc16ca6309ef191f0378faf793d1096a3e606\/pics\/movie\/celebrity-default-large.png", "medium": "https://img1.doubanio.com\/f\/movie\/8dd0c794499fe925ae2ae89ee30cd225750457b4\/pics\/movie\/celebrity-default-medium.png"}, "name": "\u66f9\u6eb1\u6a21", "id": "1345724"}], "year": "2016", "images": {"small": "https://img1.doubanio.com\/view\/movie_poster_cover\/ipst\/public\/p2384777198.jpg", "large": "https://img1.doubanio.com\/view\/movie_poster_cover\/lpst\/public\/p2384777198.jpg", "medium": "https://img1.doubanio.com\/view\/movie_poster_cover\/spst\/public\/p2384777198.jpg"}, "alt": "https:\/\/movie.douban.com\/subject\/26253737\/", "id": "26253737"}, {"rating": {"max": 10, "average": 6.7, "stars": "35", "min": 0}, "genres": ["\u5267\u60c5"], "title": "\u76db\u5148\u751f\u7684\u82b1\u513f", "casts": [{"alt": "https:\/\/movie.douban.com\/celebrity\/1040392\/", "avatars": {"small": "https://img1.doubanio.com\/img\/celebrity\/small\/47549.jpg", "large": "https://img1.doubanio.com\/img\/celebrity\/large\/47549.jpg", "medium": "https://img1.doubanio.com\/img\/celebrity\/medium\/47549.jpg"}, "name": "\u989c\u4e19\u71d5", "id": "1040392"}, {"alt": "https:\/\/movie.douban.com\/celebrity\/1316770\/", "avatars": {"small": "https://img3.doubanio.com\/img\/celebrity\/small\/1421289595.95.jpg", "large": "https://img3.doubanio.com\/img\/celebrity\/large\/1421289595.95.jpg", "medium": "https://img3.doubanio.com\/img\/celebrity\/medium\/1421289595.95.jpg"}, "name": "\u738b\u5fb7\u987a", "id": "1316770"}, {"alt": "https:\/\/movie.douban.com\/celebrity\/1276893\/", "avatars": {"small": "https://img3.doubanio.com\/img\/celebrity\/small\/43970.jpg", "large": "https://img3.doubanio.com\/img\/celebrity\/large\/43970.jpg", "medium": "https://img3.doubanio.com\/img\/celebrity\/medium\/43970.jpg"}, "name": "\u827e\u4e3d\u5a05", "id": "1276893"}], "collect_count": 63, "original_title": "\u76db\u5148\u751f\u7684\u82b1\u513f", "subtype": "movie", "directors": [{"alt": "https:\/\/movie.douban.com\/celebrity\/1358857\/", "avatars": {"small": "https://img1.doubanio.com\/img\/celebrity\/small\/1466329291.28.jpg", "large": "https://img1.doubanio.com\/img\/celebrity\/large\/1466329291.28.jpg", "medium": "https://img1.doubanio.com\/img\/celebrity\/medium\/1466329291.28.jpg"}, "name": "\u6731\u5458\u6210", "id": "1358857"}], "year": "2015", "images": {"small": "https://img1.doubanio.com\/view\/movie_poster_cover\/ipst\/public\/p2389189579.jpg", "large": "https://img1.doubanio.com\/view\/movie_poster_cover\/lpst\/public\/p2389189579.jpg", "medium": "https://img1.doubanio.com\/view\/movie_poster_cover\/spst\/public\/p2389189579.jpg"}, "alt": "https:\/\/movie.douban.com\/subject\/26779337\/", "id": "26779337"}, {"rating": {"max": 10, "average": 0, "stars": "00", "min": 0}, "genres": ["\u559c\u5267", "\u8fd0\u52a8"], "title": "\u7b11\u6797\u8db3\u7403", "casts": [{"alt": "https:\/\/movie.douban.com\/celebrity\/1275268\/", "avatars": {"small": "https://img3.doubanio.com\/img\/celebrity\/small\/19696.jpg", "large": "https://img3.doubanio.com\/img\/celebrity\/large\/19696.jpg", "medium": "https://img3.doubanio.com\/img\/celebrity\/medium\/19696.jpg"}, "name": "\u4fe1", "id": "1275268"}, {"alt": "https:\/\/movie.douban.com\/celebrity\/1314048\/", "avatars": {"small": "https://img3.doubanio.com\/img\/celebrity\/small\/22025.jpg", "large": "https://img3.doubanio.com\/img\/celebrity\/large\/22025.jpg", "medium": "https://img3.doubanio.com\/img\/celebrity\/medium\/22025.jpg"}, "name": "\u5468\u5947\u5947", "id": "1314048"}, {"alt": "https:\/\/movie.douban.com\/celebrity\/1316230\/", "avatars": {"small": "https://img1.doubanio.com\/img\/celebrity\/small\/1394666862.9.jpg", "large": "https://img1.doubanio.com\/img\/celebrity\/large\/1394666862.9.jpg", "medium": "https://img1.doubanio.com\/img\/celebrity\/medium\/1394666862.9.jpg"}, "name": "\u5f20\u7ee7\u806a", "id": "1316230"}], "collect_count": 38, "original_title": "\u7b11\u6797\u8db3\u7403", "subtype": "movie", "directors": [{"alt": "https:\/\/movie.douban.com\/celebrity\/1314402\/", "avatars": {"small": "https://img1.doubanio.com\/img\/celebrity\/small\/33988.jpg", "large": "https://img1.doubanio.com\/img\/celebrity\/large\/33988.jpg", "medium": "https://img1.doubanio.com\/img\/celebrity\/medium\/33988.jpg"}, "name": "\u6797\u5b50\u806a", "id": "1314402"}], "year": "2016", "images": {"small": "https://img3.doubanio.com\/view\/movie_poster_cover\/ipst\/public\/p2388701313.jpg", "large": "https://img3.doubanio.com\/view\/movie_poster_cover\/lpst\/public\/p2388701313.jpg", "medium": "https://img3.doubanio.com\/view\/movie_poster_cover\/spst\/public\/p2388701313.jpg"}, "alt": "https:\/\/movie.douban.com\/subject\/26547005\/", "id": "26547005"}], "title": "\u5373\u5c06\u4e0a\u6620\u7684\u7535\u5f71"}